tree_control/__init__.py
tree_control/admin.py
tree_control/apps.py
tree_control/models.py
tree_control/serializers.py
tree_control/tests.py
tree_control/views.py
tree_control/migrations/0001_initial.py
tree_control/migrations/0002_rename_type_node_identifier_and_more.py
tree_control/migrations/__init__.py
tree_control-1.0.0.dist-info/METADATA
tree_control-1.0.0.dist-info/WHEEL
tree_control-1.0.0.dist-info/top_level.txt
tree_control-1.0.0.dist-info/RECORD
